LICENSE
README.md
setup.py
EasyBeam/Beam2D.py
EasyBeam/Beam3D.py
EasyBeam/BeamAnalysis.py
EasyBeam/BeamFFRF2D.py
EasyBeam/BeamFFRF3D.py
EasyBeam/BeamPlotting.py
EasyBeam/SymbolicDerivation2D.py
EasyBeam/SymbolicDerivation3D.py
EasyBeam/__init__.py
EasyBeam.egg-info/PKG-INFO
EasyBeam.egg-info/SOURCES.txt
EasyBeam.egg-info/dependency_links.txt
EasyBeam.egg-info/requires.txt
EasyBeam.egg-info/top_level.txt
EasyBeam/__pycache__/Beam2D.cpython-310.pyc
EasyBeam/__pycache__/Beam3D.cpython-310.pyc
EasyBeam/__pycache__/BeamAnalysis.cpython-310.pyc
EasyBeam/__pycache__/BeamFFRF2D.cpython-310.pyc
EasyBeam/__pycache__/BeamFFRF3D.cpython-310.pyc
EasyBeam/__pycache__/BeamPlotting.cpython-310.pyc
EasyBeam/__pycache__/__init__.cpython-310.pyc