Metadata-Version: 2.1
Name: EasyBeam
Version: 1.1.1
Summary: Easy Application for Structural analYsis with BEAMs
Home-page: https://github.com/veiguf/EasyBeam
Author: V. Gufler, E. J. Wehrle
Author-email: veit.gufler@unibz.it
License: GNU Lesser General Public License 3.0
Platform: UNKNOWN
License-File: LICENSE
